Metadata-Version: 2.1
Name: test-ai-selenium
Version: 0.1.20
Summary: A package to bring ai to selenium scripts.
Home-page: https://github.com/test-dot-ai/testai-python-selenium
Author: Chris Navrides
Author-email: chris@test.ai
License: UNKNOWN
Project-URL: Bug Tracker, https://github.com/test-dot-ai/testai-python-selenium/issues
Platform: UNKNOWN
Classifier: Programming Language :: Python :: 3
Classifier: License :: OSI Approved :: Apache Software License
Classifier: Operating System :: OS Independent
Requires-Python: >=3.6
License-File: LICENSE
Requires-Dist: packaging
Requires-Dist: pillow
Requires-Dist: requests
Requires-Dist: selenium
